{
"type": "FeatureCollection",
"name": "random_points",
"crs": { "type": "name", "properties": { "name": "urn:ogc:def:crs:OGC:1.3:CRS84" } },
"features": [
{ "type": "Feature", "properties": { "id": 0, "price": 94759, "title": "t, consectetur adipiscin", "image": "photo2.jpg", "description": "Lorem ipsum dolor sit amet, consectetur adipiscing elit, sed do eiusmod tempor incididunt ut labore et dolor", "color": "yellow" }, "geometry": { "type": "Point", "coordinates": [ 151.13453544, -33.87579865 ] } },
{ "type": "Feature", "properties": { "id": 1, "price": 50985, "title": "em ipsum dolor sit amet, conse", "image": "photo2.jpg", "description": "Lorem ipsum dolor sit amet, consectetur adipiscing elit, sed do eiusmod tempor incididunt ut labore e", "color": "yellow" }, "geometry": { "type": "Point", "coordinates": [ 151.03395674, -33.94167852 ] } },
{ "type": "Feature", "properties": { "id": 2, "price": 82221, "title": "m dolor sit amet, cons", "image": "photo3.jpg", "description": "Lorem ipsum dolor sit amet, consectetur adipiscing elit, sed do eiusmod tempor incididunt ut labore et dolore magna aliqua. Ut enim ad ", "color": "yellow" }, "geometry": { "type": "Point", "coordinates": [ 151.194269749999989, -33.9198029 ] } },
{ "type": "Feature", "properties": { "id": 3, "price": 86297, "title": "it amet, consectetur ", "image": "photo3.jpg", "description": "Lorem ipsum dolor sit amet, consectetur adipiscing elit, sed do eiusmod tempor incididunt ut labore et dolore magna aliqua. Ut enim ad minim veniam", "color": "blue" }, "geometry": { "type": "Point", "coordinates": [ 151.0081856, -33.8633286 ] } },
{ "type": "Feature", "properties": { "id": 4, "price": 89337, "title": "consectetur adipiscing elit, s", "image": "photo2.jpg", "description": "Lorem ipsum dolor sit amet, consectetur adipiscing elit, sed do eiusmod tempor incididunt ut labore et d", "color": "blue" }, "geometry": { "type": "Point", "coordinates": [ 151.03277467, -33.89449215 ] } },
{ "type": "Feature", "properties": { "id": 5, "price": 99200, "title": "dolor sit amet, consecte", "image": "photo2.jpg", "description": "Lorem ipsum dolor sit amet, consectetur adipiscing elit, sed do eiusmod tempor incididunt ut labore et dolore magna aliqua. Ut enim ad minim ve", "color": "blue" }, "geometry": { "type": "Point", "coordinates": [ 151.13874905, -33.90118924 ] } },
{ "type": "Feature", "properties": { "id": 6, "price": 52154, "title": " do eiusmod tempor incidi", "image": "photo3.jpg", "description": "Lorem ipsum dolor sit amet, consectetur adipiscing elit, sed do eiusmod tempor incididunt ut labore et dolore magna aliq", "color": "blue" }, "geometry": { "type": "Point", "coordinates": [ 151.24499325, -33.93479292 ] } },
{ "type": "Feature", "properties": { "id": 7, "price": 97715, "title": " ut labore et dolore m", "image": "photo2.jpg", "description": "Lorem ipsum dolor sit amet, consectetur adipiscing elit, sed do eiusmod tempor incididunt ut labore et dolore magna aliqua. Ut enim", "color": "blue" }, "geometry": { "type": "Point", "coordinates": [ 151.19428819, -33.92695171 ] } },
{ "type": "Feature", "properties": { "id": 8, "price": 77554, "title": " labore et dolore magn", "image": "photo3.jpg", "description": "Lorem ipsum dolor sit amet, consectetur adipiscing elit, sed do eiusmod tempor incididunt ut labore et dolore magna aliqua. Ut ", "color": "red" }, "geometry": { "type": "Point", "coordinates": [ 150.99180123, -33.88508526 ] } },
{ "type": "Feature", "properties": { "id": 9, "price": 77767, "title": "dunt ut labore et dolore", "image": "photo1.jpg", "description": "Lorem ipsum dolor sit amet, consectetur adipiscing elit, sed do eiusmod tempor incididunt ut labore et dolore magna aliqua. Ut enim ad minim veni", "color": "red" }, "geometry": { "type": "Point", "coordinates": [ 151.22927177, -33.90517578 ] } },
{ "type": "Feature", "properties": { "id": 10, "price": 82628, "title": "piscing elit, sed do eiusm", "image": "photo2.jpg", "description": "Lorem ipsum dolor sit amet, consectetur adipiscing elit, sed do eiusmod tempor incididunt ut labore et dolor", "color": "red" }, "geometry": { "type": "Point", "coordinates": [ 150.99335736, -33.89210775 ] } },
{ "type": "Feature", "properties": { "id": 11, "price": 95300, "title": "bore et dolore magna aliqua. U", "image": "photo3.jpg", "description": "Lorem ipsum dolor sit amet, consectetur adipiscing elit, sed do eiusmod tempor incididunt ut labore et dolore magna aliqua", "color": "yellow" }, "geometry": { "type": "Point", "coordinates": [ 151.06491299000001, -33.90101729 ] } },
{ "type": "Feature", "properties": { "id": 12, "price": 62054, "title": " elit, sed do eiusmod ", "image": "photo2.jpg", "description": "Lorem ipsum dolor sit amet, consectetur adipiscing elit, sed do eiusmod tempor incididunt ut labore et", "color": "blue" }, "geometry": { "type": "Point", "coordinates": [ 151.069048579999986, -33.92398586 ] } },
{ "type": "Feature", "properties": { "id": 13, "price": 76328, "title": "ectetur adipiscing el", "image": "photo1.jpg", "description": "Lorem ipsum dolor sit amet, consectetur adipiscing elit, sed do eiusmod tempor incididunt ut labore et dolore ma", "color": "blue" }, "geometry": { "type": "Point", "coordinates": [ 151.130284350000011, -33.98102119 ] } },
{ "type": "Feature", "properties": { "id": 14, "price": 77156, "title": "ectetur adipiscing el", "image": "photo3.jpg", "description": "Lorem ipsum dolor sit amet, consectetur adipiscing elit, sed do eiusmod tempor incididunt ut labore et dolore magna aliqua. Ut enim ad minim veniam", "color": "red" }, "geometry": { "type": "Point", "coordinates": [ 151.04136748, -33.94958952 ] } },
{ "type": "Feature", "properties": { "id": 15, "price": 96850, "title": "mod tempor incididunt ut ", "image": "photo1.jpg", "description": "Lorem ipsum dolor sit amet, consectetur adipiscing elit, sed do eiusmod tempor incididunt ut labore et dolore magna aliqua. Ut", "color": "blue" }, "geometry": { "type": "Point", "coordinates": [ 151.01018756, -33.93011691 ] } },
{ "type": "Feature", "properties": { "id": 16, "price": 63458, "title": "por incididunt ut labore et", "image": "photo3.jpg", "description": "Lorem ipsum dolor sit amet, consectetur adipiscing elit, sed do eiusmod tempor incididunt ut labore et d", "color": "yellow" }, "geometry": { "type": "Point", "coordinates": [ 151.091438219999986, -33.86687236 ] } },
{ "type": "Feature", "properties": { "id": 17, "price": 83013, "title": "mod tempor incididunt u", "image": "photo1.jpg", "description": "Lorem ipsum dolor sit amet, consectetur adipiscing elit, sed do eiusmod tempor incididunt ut labore et dolore magna aliqua. Ut en", "color": "blue" }, "geometry": { "type": "Point", "coordinates": [ 151.17838536, -33.89357386 ] } },
{ "type": "Feature", "properties": { "id": 18, "price": 66902, "title": "Lorem ipsum dolor sit amet, ", "image": "photo3.jpg", "description": "Lorem ipsum dolor sit amet, consectetur adipiscing elit, sed do eiusmod tempor incididunt ut labore et dolore magna ali", "color": "red" }, "geometry": { "type": "Point", "coordinates": [ 150.98482927, -33.8722867 ] } },
{ "type": "Feature", "properties": { "id": 19, "price": 97410, "title": "re et dolore magna a", "image": "photo3.jpg", "description": "Lorem ipsum dolor sit amet, consectetur adipiscing elit, sed do eiusmod tempor incididunt ut labore et dolore magna aliqua. Ut enim ad minim v", "color": "red" }, "geometry": { "type": "Point", "coordinates": [ 151.13728663, -33.90759538 ] } },
{ "type": "Feature", "properties": { "id": 20, "price": 59001, "title": "mpor incididunt ut labor", "image": "photo2.jpg", "description": "Lorem ipsum dolor sit amet, consectetur adipiscing elit, sed do eiusmod tempor incididunt ut labore et dolore magna", "color": "red" }, "geometry": { "type": "Point", "coordinates": [ 151.091620080000013, -33.85313691 ] } },
{ "type": "Feature", "properties": { "id": 21, "price": 81304, "title": "or incididunt ut labore ", "image": "photo2.jpg", "description": "Lorem ipsum dolor sit amet, consectetur adipiscing elit, sed do eiusmod tempor incididunt ut labore et dolore magna aliqua", "color": "red" }, "geometry": { "type": "Point", "coordinates": [ 151.19289423, -33.90133165 ] } },
{ "type": "Feature", "properties": { "id": 22, "price": 80225, "title": "et, consectetur adipi", "image": "photo1.jpg", "description": "Lorem ipsum dolor sit amet, consectetur adipiscing elit, sed do eiusmod tempor incididunt ut labore et dolore magna aliqua. Ut enim ad mi", "color": "yellow" }, "geometry": { "type": "Point", "coordinates": [ 151.18218235, -33.90205699 ] } },
{ "type": "Feature", "properties": { "id": 23, "price": 59603, "title": "e et dolore magna aliqua. Ut e", "image": "photo2.jpg", "description": "Lorem ipsum dolor sit amet, consectetur adipiscing elit, sed do eiusmod tempor incididunt ut labore et dolore magna", "color": "red" }, "geometry": { "type": "Point", "coordinates": [ 151.068634479999986, -33.95017318 ] } },
{ "type": "Feature", "properties": { "id": 24, "price": 92913, "title": "lor sit amet, consec", "image": "photo1.jpg", "description": "Lorem ipsum dolor sit amet, consectetur adipiscing elit, sed do eiusmod tempor incididunt ut labore et dolore magna al", "color": "yellow" }, "geometry": { "type": "Point", "coordinates": [ 151.131557969999989, -33.87209461 ] } },
{ "type": "Feature", "properties": { "id": 25, "price": 67606, "title": "elit, sed do eiusmod tempor in", "image": "photo3.jpg", "description": "Lorem ipsum dolor sit amet, consectetur adipiscing elit, sed do eiusmod tempor incididunt ut labore et dolore magna aliqua. Ut enim", "color": "yellow" }, "geometry": { "type": "Point", "coordinates": [ 151.05778547, -33.94818458 ] } },
{ "type": "Feature", "properties": { "id": 26, "price": 85455, "title": "do eiusmod tempor incidid", "image": "photo2.jpg", "description": "Lorem ipsum dolor sit amet, consectetur adipiscing elit, sed do eiusmod tempor incididunt ut labore et dol", "color": "yellow" }, "geometry": { "type": "Point", "coordinates": [ 151.14834969, -33.9386575 ] } },
{ "type": "Feature", "properties": { "id": 27, "price": 90451, "title": "sectetur adipiscing elit,", "image": "photo2.jpg", "description": "Lorem ipsum dolor sit amet, consectetur adipiscing elit, sed do eiusmod tempor incididunt ut labore et dolore magna aliqua. Ut", "color": "blue" }, "geometry": { "type": "Point", "coordinates": [ 150.970661299999989, -33.9122783 ] } },
{ "type": "Feature", "properties": { "id": 28, "price": 86078, "title": "d tempor incididunt ut la", "image": "photo3.jpg", "description": "Lorem ipsum dolor sit amet, consectetur adipiscing elit, sed do eiusmod tempor incididunt ut labore et dolore magna aliqua. U", "color": "red" }, "geometry": { "type": "Point", "coordinates": [ 151.154197790000012, -33.88343484 ] } },
{ "type": "Feature", "properties": { "id": 29, "price": 98234, "title": "it amet, consectetur adipi", "image": "photo1.jpg", "description": "Lorem ipsum dolor sit amet, consectetur adipiscing elit, sed do eiusmod tempor incididunt ut labore et d", "color": "blue" }, "geometry": { "type": "Point", "coordinates": [ 151.16023979, -33.89441198 ] } },
{ "type": "Feature", "properties": { "id": 30, "price": 51351, "title": "usmod tempor incididunt", "image": "photo2.jpg", "description": "Lorem ipsum dolor sit amet, consectetur adipiscing elit, sed do eiusmod tempor incididunt ut labore et dolore magna aliqua. Ut enim ad minim veniam, ", "color": "blue" }, "geometry": { "type": "Point", "coordinates": [ 151.03976631, -33.93349351 ] } },
{ "type": "Feature", "properties": { "id": 31, "price": 88721, "title": "amet, consectetur adipiscing ", "image": "photo2.jpg", "description": "Lorem ipsum dolor sit amet, consectetur adipiscing elit, sed do eiusmod tempor incididunt ut labore ", "color": "yellow" }, "geometry": { "type": "Point", "coordinates": [ 151.134583709999987, -33.86410247 ] } },
{ "type": "Feature", "properties": { "id": 32, "price": 96763, "title": "m dolor sit amet, conse", "image": "photo3.jpg", "description": "Lorem ipsum dolor sit amet, consectetur adipiscing elit, sed do eiusmod tempor incididunt ut labore e", "color": "blue" }, "geometry": { "type": "Point", "coordinates": [ 150.96310946, -33.91170327 ] } },
{ "type": "Feature", "properties": { "id": 33, "price": 69091, "title": "etur adipiscing elit, sed do ", "image": "photo2.jpg", "description": "Lorem ipsum dolor sit amet, consectetur adipiscing elit, sed do eiusmod tempor incididunt ut labore et dolore magna aliqua. Ut enim ad minim v", "color": "blue" }, "geometry": { "type": "Point", "coordinates": [ 150.96534852, -33.92588774 ] } },
{ "type": "Feature", "properties": { "id": 34, "price": 55174, "title": "unt ut labore et dolore ", "image": "photo3.jpg", "description": "Lorem ipsum dolor sit amet, consectetur adipiscing elit, sed do eiusmod tempor incididunt ut labore et dolore magna aliqua. Ut enim ad minim", "color": "red" }, "geometry": { "type": "Point", "coordinates": [ 151.130819190000011, -33.8815931 ] } },
{ "type": "Feature", "properties": { "id": 35, "price": 61106, "title": " ut labore et dolore m", "image": "photo2.jpg", "description": "Lorem ipsum dolor sit amet, consectetur adipiscing elit, sed do eiusmod tempor incididunt ut labore e", "color": "red" }, "geometry": { "type": "Point", "coordinates": [ 151.09594023, -33.91943103 ] } },
{ "type": "Feature", "properties": { "id": 36, "price": 73340, "title": " sit amet, consectetur ad", "image": "photo1.jpg", "description": "Lorem ipsum dolor sit amet, consectetur adipiscing elit, sed do eiusmod tempor incididunt ut labore et dolore magna aliqua. Ut enim ad", "color": "blue" }, "geometry": { "type": "Point", "coordinates": [ 150.99778497, -33.91836555 ] } },
{ "type": "Feature", "properties": { "id": 37, "price": 91967, "title": " incididunt ut labore ", "image": "photo1.jpg", "description": "Lorem ipsum dolor sit amet, consectetur adipiscing elit, sed do eiusmod tempor incididunt ut labore et dolore m", "color": "yellow" }, "geometry": { "type": "Point", "coordinates": [ 151.0778043, -33.8949011 ] } },
{ "type": "Feature", "properties": { "id": 38, "price": 69565, "title": "etur adipiscing elit, sed do", "image": "photo3.jpg", "description": "Lorem ipsum dolor sit amet, consectetur adipiscing elit, sed do eiusmod tempor incididunt ut labore et dolore magna aliqua. Ut", "color": "yellow" }, "geometry": { "type": "Point", "coordinates": [ 151.02443279, -33.91405966 ] } },
{ "type": "Feature", "properties": { "id": 39, "price": 82462, "title": " tempor incididunt u", "image": "photo1.jpg", "description": "Lorem ipsum dolor sit amet, consectetur adipiscing elit, sed do eiusmod tempor incididunt ut labore et dolore magna aliqua. Ut enim ad", "color": "yellow" }, "geometry": { "type": "Point", "coordinates": [ 151.00502137, -33.88258749 ] } },
{ "type": "Feature", "properties": { "id": 40, "price": 63749, "title": "por incididunt ut lab", "image": "photo1.jpg", "description": "Lorem ipsum dolor sit amet, consectetur adipiscing elit, sed do eiusmod tempor incididunt ut labore et dolore magna aliqua. Ut enim ad minim veni", "color": "yellow" }, "geometry": { "type": "Point", "coordinates": [ 151.143277469999987, -33.89634077 ] } },
{ "type": "Feature", "properties": { "id": 41, "price": 69926, "title": " sit amet, consectetur ad", "image": "photo2.jpg", "description": "Lorem ipsum dolor sit amet, consectetur adipiscing elit, sed do eiusmod tempor incididunt ut labore et dolore magna aliqua. Ut ", "color": "red" }, "geometry": { "type": "Point", "coordinates": [ 151.08600708, -33.9683376 ] } },
{ "type": "Feature", "properties": { "id": 42, "price": 58862, "title": "g elit, sed do eiusmod", "image": "photo1.jpg", "description": "Lorem ipsum dolor sit amet, consectetur adipiscing elit, sed do eiusmod tempor incididunt ut labore et dolore magna aliqua. Ut enim ad minim ", "color": "blue" }, "geometry": { "type": "Point", "coordinates": [ 151.09191945, -33.89193154 ] } },
{ "type": "Feature", "properties": { "id": 43, "price": 88677, "title": "onsectetur adipiscing eli", "image": "photo1.jpg", "description": "Lorem ipsum dolor sit amet, consectetur adipiscing elit, sed do eiusmod tempor incididunt ut labore et dolore magna aliqua. Ut enim ad mini", "color": "yellow" }, "geometry": { "type": "Point", "coordinates": [ 151.03176951, -33.89016719 ] } },
{ "type": "Feature", "properties": { "id": 44, "price": 77237, "title": "onsectetur adipiscing e", "image": "photo3.jpg", "description": "Lorem ipsum dolor sit amet, consectetur adipiscing elit, sed do eiusmod tempor incididunt ut labore et dolore magna aliqua. Ut enim ad minim veniam, ", "color": "yellow" }, "geometry": { "type": "Point", "coordinates": [ 151.064127109999987, -33.94672511 ] } },
{ "type": "Feature", "properties": { "id": 45, "price": 57870, "title": "ing elit, sed do eiusmod ", "image": "photo3.jpg", "description": "Lorem ipsum dolor sit amet, consectetur adipiscing elit, sed do eiusmod tempor incididunt ut labore et dolore magna aliqua. Ut enim ad minim", "color": "blue" }, "geometry": { "type": "Point", "coordinates": [ 151.14937168, -33.92433927 ] } },
{ "type": "Feature", "properties": { "id": 46, "price": 99608, "title": "ipsum dolor sit amet, consecte", "image": "photo2.jpg", "description": "Lorem ipsum dolor sit amet, consectetur adipiscing elit, sed do eiusmod tempor incididunt ut labore et dol", "color": "yellow" }, "geometry": { "type": "Point", "coordinates": [ 150.97201678, -33.90990315 ] } },
{ "type": "Feature", "properties": { "id": 47, "price": 66061, "title": " dolor sit amet, consectetur", "image": "photo1.jpg", "description": "Lorem ipsum dolor sit amet, consectetur adipiscing elit, sed do eiusmod tempor incididunt ut labore et dolore magna aliqua. Ut enim ", "color": "red" }, "geometry": { "type": "Point", "coordinates": [ 151.0191845, -33.86682347 ] } },
{ "type": "Feature", "properties": { "id": 48, "price": 79233, "title": "psum dolor sit amet, conse", "image": "photo1.jpg", "description": "Lorem ipsum dolor sit amet, consectetur adipiscing elit, sed do eiusmod tempor incididunt ut labore et dolore magna aliqua. Ut e", "color": "yellow" }, "geometry": { "type": "Point", "coordinates": [ 151.03448488, -33.95139815 ] } },
{ "type": "Feature", "properties": { "id": 49, "price": 81684, "title": "incididunt ut labore et dol", "image": "photo2.jpg", "description": "Lorem ipsum dolor sit amet, consectetur adipiscing elit, sed do eiusmod tempor incididunt ut labore et dolore magna aliqua. Ut enim ad minim venia", "color": "red" }, "geometry": { "type": "Point", "coordinates": [ 151.06115037, -33.94215191 ] } },
{ "type": "Feature", "properties": { "id": 50, "price": 60843, "title": "ut labore et dolore magna ", "image": "photo3.jpg", "description": "Lorem ipsum dolor sit amet, consectetur adipiscing elit, sed do eiusmod tempor incididunt ut labore et dolore magna aliqua. Ut eni", "color": "blue" }, "geometry": { "type": "Point", "coordinates": [ 151.23047822, -33.92277196 ] } },
{ "type": "Feature", "properties": { "id": 51, "price": 99764, "title": "scing elit, sed do eiu", "image": "photo2.jpg", "description": "Lorem ipsum dolor sit amet, consectetur adipiscing elit, sed do eiusmod tempor incididunt ut labore et dolore magna aliqua. Ut enim ad minim ve", "color": "blue" }, "geometry": { "type": "Point", "coordinates": [ 151.21303597, -33.95330921 ] } },
{ "type": "Feature", "properties": { "id": 52, "price": 58007, "title": "re et dolore magna aliqua. Ut", "image": "photo1.jpg", "description": "Lorem ipsum dolor sit amet, consectetur adipiscing elit, sed do eiusmod tempor incididunt ut labore et dolore magna aliqua. Ut eni", "color": "red" }, "geometry": { "type": "Point", "coordinates": [ 151.13761148, -33.92488899 ] } },
{ "type": "Feature", "properties": { "id": 53, "price": 82584, "title": "tempor incididunt ut labore", "image": "photo2.jpg", "description": "Lorem ipsum dolor sit amet, consectetur adipiscing elit, sed do eiusmod tempor incididunt ut labore et dolore ma", "color": "blue" }, "geometry": { "type": "Point", "coordinates": [ 151.07225291, -33.89921411 ] } },
{ "type": "Feature", "properties": { "id": 54, "price": 97894, "title": "met, consectetur adipiscing", "image": "photo3.jpg", "description": "Lorem ipsum dolor sit amet, consectetur adipiscing elit, sed do eiusmod tempor incididunt ut labore et d", "color": "red" }, "geometry": { "type": "Point", "coordinates": [ 151.21168505, -33.94799878 ] } },
{ "type": "Feature", "properties": { "id": 55, "price": 78002, "title": "empor incididunt ut labore et ", "image": "photo3.jpg", "description": "Lorem ipsum dolor sit amet, consectetur adipiscing elit, sed do eiusmod tempor incididunt ut labore et dolore magna aliqua. Ut enim ad ", "color": "blue" }, "geometry": { "type": "Point", "coordinates": [ 151.205097599999988, -33.93847027 ] } },
{ "type": "Feature", "properties": { "id": 56, "price": 51012, "title": "iusmod tempor incidi", "image": "photo2.jpg", "description": "Lorem ipsum dolor sit amet, consectetur adipiscing elit, sed do eiusmod tempor incididunt ut labore et d", "color": "yellow" }, "geometry": { "type": "Point", "coordinates": [ 151.07960472, -33.9678725 ] } },
{ "type": "Feature", "properties": { "id": 57, "price": 80425, "title": "t amet, consectetur a", "image": "photo3.jpg", "description": "Lorem ipsum dolor sit amet, consectetur adipiscing elit, sed do eiusmod tempor incididunt ut labore et dolore", "color": "red" }, "geometry": { "type": "Point", "coordinates": [ 151.09995235, -33.86496222 ] } },
{ "type": "Feature", "properties": { "id": 58, "price": 62166, "title": "ore et dolore magna aliqua. Ut", "image": "photo1.jpg", "description": "Lorem ipsum dolor sit amet, consectetur adipiscing elit, sed do eiusmod tempor incididunt ut labore et dolore magna aliqua. Ut enim ", "color": "yellow" }, "geometry": { "type": "Point", "coordinates": [ 151.079528259999989, -33.88515778 ] } },
{ "type": "Feature", "properties": { "id": 59, "price": 84266, "title": "ng elit, sed do eius", "image": "photo3.jpg", "description": "Lorem ipsum dolor sit amet, consectetur adipiscing elit, sed do eiusmod tempor incididunt ut labore et dolore magna aliqua. Ut enim ad minim ven", "color": "red" }, "geometry": { "type": "Point", "coordinates": [ 150.991173120000013, -33.89640308 ] } },
{ "type": "Feature", "properties": { "id": 60, "price": 59260, "title": "or incididunt ut labore et dol", "image": "photo3.jpg", "description": "Lorem ipsum dolor sit amet, consectetur adipiscing elit, sed do eiusmod tempor incididunt ut labore e", "color": "blue" }, "geometry": { "type": "Point", "coordinates": [ 151.04297864, -33.93105016 ] } },
{ "type": "Feature", "properties": { "id": 61, "price": 95949, "title": "mod tempor incididunt ut la", "image": "photo2.jpg", "description": "Lorem ipsum dolor sit amet, consectetur adipiscing elit, sed do eiusmod tempor incididunt ut labore et dolore magna aliqua. Ut enim", "color": "yellow" }, "geometry": { "type": "Point", "coordinates": [ 151.04465226, -33.91918487 ] } },
{ "type": "Feature", "properties": { "id": 62, "price": 87817, "title": "ipsum dolor sit amet,", "image": "photo1.jpg", "description": "Lorem ipsum dolor sit amet, consectetur adipiscing elit, sed do eiusmod tempor incididunt ut labore et dolore magna aliqua. Ut e", "color": "yellow" }, "geometry": { "type": "Point", "coordinates": [ 150.99703312, -33.8953235 ] } },
{ "type": "Feature", "properties": { "id": 63, "price": 79816, "title": "adipiscing elit, sed ", "image": "photo1.jpg", "description": "Lorem ipsum dolor sit amet, consectetur adipiscing elit, sed do eiusmod tempor incididunt ut labore et dolore magn", "color": "yellow" }, "geometry": { "type": "Point", "coordinates": [ 151.22371734, -33.8822098 ] } },
{ "type": "Feature", "properties": { "id": 64, "price": 65643, "title": "piscing elit, sed do eiusmo", "image": "photo1.jpg", "description": "Lorem ipsum dolor sit amet, consectetur adipiscing elit, sed do eiusmod tempor incididunt ut labore et dolore mag", "color": "yellow" }, "geometry": { "type": "Point", "coordinates": [ 151.08577148, -33.8826278 ] } },
{ "type": "Feature", "properties": { "id": 65, "price": 72286, "title": "unt ut labore et dol", "image": "photo1.jpg", "description": "Lorem ipsum dolor sit amet, consectetur adipiscing elit, sed do eiusmod tempor incididunt ut labore et dolore magna aliqua. Ut enim ad mini", "color": "blue" }, "geometry": { "type": "Point", "coordinates": [ 150.971690349999989, -33.93187077 ] } },
{ "type": "Feature", "properties": { "id": 66, "price": 66794, "title": "orem ipsum dolor sit a", "image": "photo2.jpg", "description": "Lorem ipsum dolor sit amet, consectetur adipiscing elit, sed do eiusmod tempor incididunt ut labore et dolore magna aliqua", "color": "yellow" }, "geometry": { "type": "Point", "coordinates": [ 151.061036, -33.88440094 ] } },
{ "type": "Feature", "properties": { "id": 67, "price": 90378, "title": "didunt ut labore et dolore ", "image": "photo2.jpg", "description": "Lorem ipsum dolor sit amet, consectetur adipiscing elit, sed do eiusmod tempor incididunt ut labore et dolore magna aliqua. Ut enim a", "color": "red" }, "geometry": { "type": "Point", "coordinates": [ 151.103576510000011, -33.89290243 ] } },
{ "type": "Feature", "properties": { "id": 68, "price": 85547, "title": "cididunt ut labore et dolor", "image": "photo1.jpg", "description": "Lorem ipsum dolor sit amet, consectetur adipiscing elit, sed do eiusmod tempor incididunt ut labore et dolore ma", "color": "red" }, "geometry": { "type": "Point", "coordinates": [ 151.00778753, -33.87435042 ] } },
{ "type": "Feature", "properties": { "id": 69, "price": 92649, "title": "e et dolore magna aliqua.", "image": "photo2.jpg", "description": "Lorem ipsum dolor sit amet, consectetur adipiscing elit, sed do eiusmod tempor incididunt ut labore et dolo", "color": "blue" }, "geometry": { "type": "Point", "coordinates": [ 151.17570938, -33.93336865 ] } },
{ "type": "Feature", "properties": { "id": 70, "price": 80185, "title": "nt ut labore et dolore magna a", "image": "photo3.jpg", "description": "Lorem ipsum dolor sit amet, consectetur adipiscing elit, sed do eiusmod tempor incididunt ut labore et dolore magna aliqua. Ut enim ad minim veniam, q", "color": "red" }, "geometry": { "type": "Point", "coordinates": [ 151.090865470000011, -33.84795776 ] } },
{ "type": "Feature", "properties": { "id": 71, "price": 55204, "title": "incididunt ut labore ", "image": "photo3.jpg", "description": "Lorem ipsum dolor sit amet, consectetur adipiscing elit, sed do eiusmod tempor incididunt ut labore et dolore magna aliqua. Ut eni", "color": "blue" }, "geometry": { "type": "Point", "coordinates": [ 151.08748143, -33.94940479 ] } },
{ "type": "Feature", "properties": { "id": 72, "price": 80768, "title": "sectetur adipiscing elit, s", "image": "photo2.jpg", "description": "Lorem ipsum dolor sit amet, consectetur adipiscing elit, sed do eiusmod tempor incididunt ut labore et dolor", "color": "yellow" }, "geometry": { "type": "Point", "coordinates": [ 151.17399088, -33.91796702 ] } },
{ "type": "Feature", "properties": { "id": 73, "price": 68455, "title": "d do eiusmod tempor incid", "image": "photo3.jpg", "description": "Lorem ipsum dolor sit amet, consectetur adipiscing elit, sed do eiusmod tempor incididunt ut labore et dolore magna aliqua. Ut enim ad mini", "color": "yellow" }, "geometry": { "type": "Point", "coordinates": [ 151.00136727, -33.92529328 ] } },
{ "type": "Feature", "properties": { "id": 74, "price": 65501, "title": ", consectetur adipis", "image": "photo2.jpg", "description": "Lorem ipsum dolor sit amet, consectetur adipiscing elit, sed do eiusmod tempor incididunt ut labore e", "color": "red" }, "geometry": { "type": "Point", "coordinates": [ 151.09847423, -33.97198973 ] } },
{ "type": "Feature", "properties": { "id": 75, "price": 94404, "title": "d tempor incididunt ut labore ", "image": "photo2.jpg", "description": "Lorem ipsum dolor sit amet, consectetur adipiscing elit, sed do eiusmod tempor incididunt ut labore et do", "color": "yellow" }, "geometry": { "type": "Point", "coordinates": [ 151.22332191000001, -33.87986197 ] } },
{ "type": "Feature", "properties": { "id": 76, "price": 62792, "title": "iscing elit, sed do eiusmod ", "image": "photo3.jpg", "description": "Lorem ipsum dolor sit amet, consectetur adipiscing elit, sed do eiusmod tempor incididunt ut labore et dolore magna aliqua. Ut enim ad minim veniam,", "color": "red" }, "geometry": { "type": "Point", "coordinates": [ 151.01825301, -33.85462917 ] } },
{ "type": "Feature", "properties": { "id": 77, "price": 97630, "title": "mod tempor incididunt ", "image": "photo1.jpg", "description": "Lorem ipsum dolor sit amet, consectetur adipiscing elit, sed do eiusmod tempor incididunt ut labore et dolore magna aliqua. Ut eni", "color": "blue" }, "geometry": { "type": "Point", "coordinates": [ 151.06597259, -33.85417193 ] } },
{ "type": "Feature", "properties": { "id": 78, "price": 97170, "title": "or sit amet, consectetu", "image": "photo1.jpg", "description": "Lorem ipsum dolor sit amet, consectetur adipiscing elit, sed do eiusmod tempor incididunt ut labore ", "color": "yellow" }, "geometry": { "type": "Point", "coordinates": [ 151.25999951, -33.9126589 ] } },
{ "type": "Feature", "properties": { "id": 79, "price": 57977, "title": "didunt ut labore et dolore", "image": "photo3.jpg", "description": "Lorem ipsum dolor sit amet, consectetur adipiscing elit, sed do eiusmod tempor incididunt ut labore et dolore magna aliqua. Ut enim ad minim v", "color": "red" }, "geometry": { "type": "Point", "coordinates": [ 151.218182829999989, -33.892449 ] } },
{ "type": "Feature", "properties": { "id": 80, "price": 84952, "title": "adipiscing elit, sed do ei", "image": "photo1.jpg", "description": "Lorem ipsum dolor sit amet, consectetur adipiscing elit, sed do eiusmod tempor incididunt ut labore et dolore magna aliqua. Ut enim ad m", "color": "blue" }, "geometry": { "type": "Point", "coordinates": [ 151.06886781, -33.89220376 ] } },
{ "type": "Feature", "properties": { "id": 81, "price": 76272, "title": "cing elit, sed do eiusm", "image": "photo3.jpg", "description": "Lorem ipsum dolor sit amet, consectetur adipiscing elit, sed do eiusmod tempor incididunt ut labore et dolore ", "color": "yellow" }, "geometry": { "type": "Point", "coordinates": [ 151.188928729999986, -33.92983141 ] } },
{ "type": "Feature", "properties": { "id": 82, "price": 67842, "title": " sed do eiusmod tempor incidi", "image": "photo1.jpg", "description": "Lorem ipsum dolor sit amet, consectetur adipiscing elit, sed do eiusmod tempor incididunt ut labore et dolore magna aliqua. Ut enim ad ", "color": "red" }, "geometry": { "type": "Point", "coordinates": [ 150.98398803, -33.8975746 ] } },
{ "type": "Feature", "properties": { "id": 83, "price": 65794, "title": "em ipsum dolor sit amet, ", "image": "photo1.jpg", "description": "Lorem ipsum dolor sit amet, consectetur adipiscing elit, sed do eiusmod tempor incididunt ut labore et dolore magna ali", "color": "blue" }, "geometry": { "type": "Point", "coordinates": [ 151.172123989999989, -33.92107553 ] } },
{ "type": "Feature", "properties": { "id": 84, "price": 70994, "title": "it amet, consectetur adipis", "image": "photo2.jpg", "description": "Lorem ipsum dolor sit amet, consectetur adipiscing elit, sed do eiusmod tempor incididunt ut labore et dolore magna ali", "color": "yellow" }, "geometry": { "type": "Point", "coordinates": [ 150.99083474, -33.94580503 ] } },
{ "type": "Feature", "properties": { "id": 85, "price": 68736, "title": "idunt ut labore et dolor", "image": "photo1.jpg", "description": "Lorem ipsum dolor sit amet, consectetur adipiscing elit, sed do eiusmod tempor incididunt ut labore et dolore magna aliqua. Ut eni", "color": "yellow" }, "geometry": { "type": "Point", "coordinates": [ 151.17087605, -33.87782255 ] } },
{ "type": "Feature", "properties": { "id": 86, "price": 68930, "title": " sit amet, consectetur ad", "image": "photo3.jpg", "description": "Lorem ipsum dolor sit amet, consectetur adipiscing elit, sed do eiusmod tempor incididunt ut labore et dolore magna aliqua", "color": "blue" }, "geometry": { "type": "Point", "coordinates": [ 151.004485280000011, -33.93123138 ] } },
{ "type": "Feature", "properties": { "id": 87, "price": 68019, "title": "ididunt ut labore et ", "image": "photo3.jpg", "description": "Lorem ipsum dolor sit amet, consectetur adipiscing elit, sed do eiusmod tempor incididunt ut labore et dolore magna aliqua. Ut enim ad minim veniam", "color": "blue" }, "geometry": { "type": "Point", "coordinates": [ 151.160990340000012, -33.93251528 ] } },
{ "type": "Feature", "properties": { "id": 88, "price": 65962, "title": "idunt ut labore et dolore", "image": "photo2.jpg", "description": "Lorem ipsum dolor sit amet, consectetur adipiscing elit, sed do eiusmod tempor incididunt ut labore et dolore magna aliqua. Ut enim ad minim", "color": "red" }, "geometry": { "type": "Point", "coordinates": [ 151.000607620000011, -33.89879478 ] } },
{ "type": "Feature", "properties": { "id": 89, "price": 68325, "title": "sum dolor sit amet, ", "image": "photo1.jpg", "description": "Lorem ipsum dolor sit amet, consectetur adipiscing elit, sed do eiusmod tempor incididunt ut labore et dolore magna aliqua. Ut enim ad minim veni", "color": "red" }, "geometry": { "type": "Point", "coordinates": [ 151.0795818, -33.93236902 ] } },
{ "type": "Feature", "properties": { "id": 90, "price": 72750, "title": "met, consectetur adip", "image": "photo1.jpg", "description": "Lorem ipsum dolor sit amet, consectetur adipiscing elit, sed do eiusmod tempor incididunt ut labore et dolore magna aliqua. Ut enim ad m", "color": "yellow" }, "geometry": { "type": "Point", "coordinates": [ 151.21470736, -33.92759667 ] } },
{ "type": "Feature", "properties": { "id": 91, "price": 96911, "title": " dolor sit amet, consect", "image": "photo1.jpg", "description": "Lorem ipsum dolor sit amet, consectetur adipiscing elit, sed do eiusmod tempor incididunt ut labore et dolore magna aliqua. Ut enim ad minim venia", "color": "blue" }, "geometry": { "type": "Point", "coordinates": [ 150.98501536, -33.87610538 ] } },
{ "type": "Feature", "properties": { "id": 92, "price": 62115, "title": "nt ut labore et dolore ma", "image": "photo3.jpg", "description": "Lorem ipsum dolor sit amet, consectetur adipiscing elit, sed do eiusmod tempor incididunt ut labore et dolore magna a", "color": "red" }, "geometry": { "type": "Point", "coordinates": [ 151.06046916, -33.9639962 ] } },
{ "type": "Feature", "properties": { "id": 93, "price": 75833, "title": " sit amet, consectetu", "image": "photo1.jpg", "description": "Lorem ipsum dolor sit amet, consectetur adipiscing elit, sed do eiusmod tempor incididunt ut labore et dolore magna aliqua. Ut enim ad minim v", "color": "blue" }, "geometry": { "type": "Point", "coordinates": [ 151.12364851000001, -33.88422873 ] } },
{ "type": "Feature", "properties": { "id": 94, "price": 67101, "title": "ur adipiscing elit, sed do ", "image": "photo1.jpg", "description": "Lorem ipsum dolor sit amet, consectetur adipiscing elit, sed do eiusmod tempor incididunt ut labore et dolore magna aliqua. Ut enim ad minim veniam", "color": "blue" }, "geometry": { "type": "Point", "coordinates": [ 151.009628819999989, -33.92633173 ] } },
{ "type": "Feature", "properties": { "id": 95, "price": 51714, "title": "mod tempor incididunt ut", "image": "photo3.jpg", "description": "Lorem ipsum dolor sit amet, consectetur adipiscing elit, sed do eiusmod tempor incididunt ut labore et do", "color": "blue" }, "geometry": { "type": "Point", "coordinates": [ 151.13958132, -33.95307561 ] } },
{ "type": "Feature", "properties": { "id": 96, "price": 92174, "title": "lit, sed do eiusmod t", "image": "photo3.jpg", "description": "Lorem ipsum dolor sit amet, consectetur adipiscing elit, sed do eiusmod tempor incididunt ut labore et dolor", "color": "red" }, "geometry": { "type": "Point", "coordinates": [ 150.99918093, -33.8740288 ] } },
{ "type": "Feature", "properties": { "id": 97, "price": 56596, "title": " sit amet, consectetur ad", "image": "photo3.jpg", "description": "Lorem ipsum dolor sit amet, consectetur adipiscing elit, sed do eiusmod tempor incididunt ut labore et dolore magna aliqua. Ut enim ad ", "color": "blue" }, "geometry": { "type": "Point", "coordinates": [ 151.07942703, -33.91683751 ] } },
{ "type": "Feature", "properties": { "id": 98, "price": 66959, "title": "e et dolore magna aliqua. Ut e", "image": "photo3.jpg", "description": "Lorem ipsum dolor sit amet, consectetur adipiscing elit, sed do eiusmod tempor incididunt ut labore et dolore magna aliqua. Ut enim ad minim veniam, ", "color": "red" }, "geometry": { "type": "Point", "coordinates": [ 151.08898922, -33.97693705 ] } },
{ "type": "Feature", "properties": { "id": 99, "price": 51884, "title": "nt ut labore et dolore magna ", "image": "photo3.jpg", "description": "Lorem ipsum dolor sit amet, consectetur adipiscing elit, sed do eiusmod tempor incididunt ut labore et dolore magna aliqua. Ut enim ", "color": "yellow" }, "geometry": { "type": "Point", "coordinates": [ 150.99732217, -33.9189746 ] } }
]
}
